Workbook

Sheet 1_Monthly_Waterfall
A1: Waterfall Cash-Flow Allocation — Monthly Validation
A2: All amounts in ₹ Lakh (10⁵). Senior → Mezz → Cash Reserve → Equity. Loss allocation is bottom-up: equity (rank 3) absorbs first.
A4: Reporting Date | B4: 1. Servicer Fee | C4: 2. Trustee Fee | D4: 3. Senior Interest | E4: 4. Mezz Interest | F4: 5. Senior Principal | G4: 6. Mezz Principal | H4: 7. Cash Reserve Top-up | I4: 8. Loss → Equity | J4: 9. Loss → Mezz | K4: 10. Loss → Senior | L4: 11. Equity Residual | M4: Total Out (Senior + Mezz + Equity) | N4: Check (=∑ fees + interest + principal + reserve + residual)
A5: 45290 | B5: 2.2754167 | C5: 2 | D5: 30.036875 | E5: 5.73125 | F5: 170.74713 | G5: 0 | H5: 0 | I5: 8.1502512 | J5: 0 | K5: 0 | L5: 0 | M5: =D5+E5+F5+G5+L5 | N5: =B5+C5+D5+E5+F5+G5+H5+L5
A6: 45321 | B6: 2.2008761 | C6: 2 | D6: 28.862988 | E6: 5.73125 | F6: 146.54627 | G6: 0 | H6: 0 | I6: 8.5128026 | J6: 0 | K6: 0 | L6: 0 | M6: =D6+E6+F6+G6+L6 | N6: =B6+C6+D6+E6+F6+G6+H6+L6
A7: 45350 | B7: 2.1362681 | C7: 2 | D7: 27.855483 | E7: 5.73125 | F7: 162.9027 | G7: 0 | H7: 0 | I7: 7.2611336 | J7: 0 | K7: 0 | L7: 0 | M7: =D7+E7+F7+G7+L7 | N7: =B7+C7+D7+E7+F7+G7+H7+L7
A8: 45381 | B8: 2.0653665 | C8: 2 | D8: 26.735527 | E8: 5.73125 | F8: 171.40405 | G8: 0 | H8: 0 | I8: 7.7816842 | J8: 0 | K8: 0 | L8: 0 | M8: =D8+E8+F8+G8+L8 | N8: =B8+C8+D8+E8+F8+G8+H8+L8
A9: 45412 | B9: 1.9907058 | C9: 2 | D9: 25.557124 | E9: 5.73125 | F9: 176.94501 | G9: 0 | H9: 0 | I9: 7.1115234 | J9: 0 | K9: 0 | L9: 0 | M9: =D9+E9+F9+G9+L9 | N9: =B9+C9+D9+E9+F9+G9+H9+L9
A10: 45442 | B10: 3.7607149 | C10: 4 | D10: 47.636182 | E10: 11.4625 | F10: 318.29118 | G10: 0 | H10: 0 | I10: 15.33672 | J10: 0 | K10: 0 | L10: 0 | M10: =D10+E10+F10+G10+L10 | N10: =B10+C10+D10+E10+F10+G10+H10+L10
A11: 45473 | B11: 1.775004 | C11: 2 | D11: 22.152375 | E11: 5.73125 | F11: 152.09407 | G11: 0 | H11: 0 | I11: 4.5818697 | J11: 0 | K11: 0 | L11: 0 | M11: =D11+E11+F11+G11+L11 | N11: =B11+C11+D11+E11+F11+G11+H11+L11
A12: 45503 | B12: 1.7097223 | C12: 2 | D12: 21.106728 | E12: 5.73125 | F12: 131.33982 | G12: 0 | H12: 0 | I12: 5.338392 | J12: 0 | K12: 0 | L12: 0 | M12: =D12+E12+F12+G12+L12 | N12: =B12+C12+D12+E12+F12+G12+H12+L12
A13: 45534 | B13: 1.6527731 | C13: 2 | D13: 20.203767 | E13: 5.73125 | F13: 155.29073 | G13: 0 | H13: 0 | I13: 5.5417654 | J13: 0 | K13: 0 | L13: 0 | M13: =D13+E13+F13+G13+L13 | N13: =B13+C13+D13+E13+F13+G13+H13+L13
A14: 45565 | B14: 1.5857595 | C14: 2 | D14: 19.136143 | E14: 5.73125 | F14: 133.53419 | G14: 0 | H14: 0 | I14: 4.0347926 | J14: 0 | K14: 0 | L14: 0 | M14: =D14+E14+F14+G14+L14 | N14: =B14+C14+D14+E14+F14+G14+H14+L14
A15: 45595 | B15: 1.5284391 | C15: 2 | D15: 18.218096 | E15: 5.73125 | F15: 121.09153 | G15: 0 | H15: 0 | I15: 4.1906215 | J15: 0 | K15: 0 | L15: 0 | M15: =D15+E15+F15+G15+L15 | N15: =B15+C15+D15+E15+F15+G15+H15+L15
A17: TOTAL | B17: =SUM(B5:B15) | C17: =SUM(C5:C15) | D17: =SUM(D5:D15) | E17: =SUM(E5:E15) | F17: =SUM(F5:F15) | G17: =SUM(G5:G15) | H17: =SUM(H5:H15) | I17: =SUM(I5:I15) | ... N17: =SUM(N5:N15)

Sheet 2_Pipeline_CrossCheck
A1: Excel Total vs. Python Pipeline Output
A2: Both totals are computed from the same monthly waterfall.csv but via independent paths. Delta should be ≈ 0.
A4: Step | B4: Pipeline Total (₹ Lakh) | C4: Excel Total (₹ Lakh) | D4: Delta | E4: Status
A5: servicer_fee | B5: 22.681046 | C5: ='1_Monthly_Waterfall'!B17 | D5: =C5-B5 | E5: =IF(ABS(D5) <= 0.01, "✓ PASS", "✗ FAIL")
A6: trustee_fee | B6: 24 | C6: ='1_Monthly_Waterfall'!C17 | D6: =C6-B6 | E6: =IF(ABS(D6) <= 0.01, "✓ PASS", "✗ FAIL")
A7: senior_interest | B7: 287.50129 | C7: ='1_Monthly_Waterfall'!D17 | D7: =C7-B7 | E7: =IF(ABS(D7) <= 0.01, "✓ PASS", "✗ FAIL")
A8: mezz_interest | B8: 68.775 | C8: ='1_Monthly_Waterfall'!E17 | D8: =C8-B8 | E8: =IF(ABS(D8) <= 0.01, "✓ PASS", "✗ FAIL")
A9: senior_principal | B9: 1840.1867 | C9: ='1_Monthly_Waterfall'!F17 | D9: =C9-B9 | E9: =IF(ABS(D9) <= 0.01, "✓ PASS", "✗ FAIL")
A10: mezz_principal | B10: 0 | C10: ='1_Monthly_Waterfall'!G17 | D10: =C10-B10 | E10: =IF(ABS(D10) <= 0.01, "✓ PASS", "✗ FAIL")
A11: cash_reserve_topup | B11: 0 | C11: ='1_Monthly_Waterfall'!H17 | D11: =C11-B11 | E11: =IF(ABS(D11) <= 0.01, "✓ PASS", "✗ FAIL")
A12: loss_to_rank_3 | B12: 77.841556 | C12: ='1_Monthly_Waterfall'!I17 | D12: =C12-B12 | E12: =IF(ABS(D12) <= 0.01, "✓ PASS", "✗ FAIL")
A13: loss_to_rank_2 | B13: 0 | C13: ='1_Monthly_Waterfall'!J17 | D13: =C13-B13 | E13: =IF(ABS(D13) <= 0.01, "✓ PASS", "✗ FAIL")
A14: loss_to_rank_1 | B14: 0 | C14: ='1_Monthly_Waterfall'!K17 | D14: =C14-B14 | E14: =IF(ABS(D14) <= 0.01, "✓ PASS", "✗ FAIL")
A15: equity_residual | B15: 0 | C15: ='1_Monthly_Waterfall'!L17 | D15: =C15-B15 | E15: =IF(ABS(D15) <= 0.01, "✓ PASS", "✗ FAIL")

Sheet 3_Trigger_Status
A1: Securitisation Triggers — Threshold Status
A2: Thresholds per RBI Master Direction §22.6 and indenture covenants. Yellow cells = configurable assumptions.
A4: Trigger | B4: Current Value | C4: Threshold | D4: Status | E4: Comment
A5: 30+ DPD % | B5: 0.1411 | C5: 0.06 | D5: =IF(B5 > C5, "BREACHED", "OK") | E5: Early-amortisation trigger if breached
A6: Cumulative Net Loss % | B6: 0.0214 | C6: 0.03 | D6: =IF(B6 > C6, "BREACHED", "OK") | E6: Senior-step-up trigger
A7: OC Ratio (pool / senior) | B7: 1.165 | C7: 1.15 | D7: =IF(B7 < C7, "BREACHED", "OK") | E7: Trapping trigger if below floor
A8: CPR Annualised % | B8: 0.0933 | C8: 0.2 | D8: =IF(B8 > C8, "BREACHED", "OK") | E8: Acceptable prepayment range
